.gitignore
LICENSE
Makefile
NOTICES.txt
README.md
pyproject.toml
.github/CODEOWNERS
.github/workflows/check.yml
.github/workflows/publish.yml
.vscode/settings.json
docs/api/.buildinfo
docs/api/genindex.html
docs/api/hutch.html
docs/api/hutch.security.annotation.html
docs/api/hutch.security.html
docs/api/hutch.security.jupiterone.constants.html
docs/api/hutch.security.jupiterone.exceptions.html
docs/api/hutch.security.jupiterone.html
docs/api/hutch.security.jupiterone.models.html
docs/api/hutch.security.jupiterone.queries.html
docs/api/hutch.security.jupiterone.query.html
docs/api/hutch.security.parsers.cloudtrail.html
docs/api/hutch.security.parsers.exceptions.html
docs/api/hutch.security.parsers.html
docs/api/hutch.security.sumologic.base.html
docs/api/hutch.security.sumologic.constants.html
docs/api/hutch.security.sumologic.exceptions.html
docs/api/hutch.security.sumologic.html
docs/api/hutch.security.sumologic.models.html
docs/api/hutch.security.sumologic.search.html
docs/api/index.html
docs/api/modules.html
docs/api/objects.inv
docs/api/py-modindex.html
docs/api/search.html
docs/api/searchindex.js
docs/api/_modules/index.html
docs/api/_modules/hutch/security/jupiterone/exceptions.html
docs/api/_modules/hutch/security/jupiterone/models.html
docs/api/_modules/hutch/security/jupiterone/query.html
docs/api/_modules/hutch/security/parsers/cloudtrail.html
docs/api/_modules/hutch/security/parsers/exceptions.html
docs/api/_modules/hutch/security/sumologic/base.html
docs/api/_modules/hutch/security/sumologic/exceptions.html
docs/api/_modules/hutch/security/sumologic/models.html
docs/api/_modules/hutch/security/sumologic/search.html
docs/api/_sources/hutch.rst.txt
docs/api/_sources/hutch.security.annotation.rst.txt
docs/api/_sources/hutch.security.jupiterone.constants.rst.txt
docs/api/_sources/hutch.security.jupiterone.exceptions.rst.txt
docs/api/_sources/hutch.security.jupiterone.models.rst.txt
docs/api/_sources/hutch.security.jupiterone.queries.rst.txt
hutch_security.egg-info/PKG-INFO
hutch_security.egg-info/SOURCES.txt
hutch_security.egg-info/dependency_links.txt
hutch_security.egg-info/requires.txt
hutch_security.egg-info/top_level.txt
